apifoncier/__init__.py
apifoncier/client.py
apifoncier/config.py
apifoncier/exceptions.py
apifoncier/validators.py
apifoncier/endpoints/__init__.py
apifoncier/endpoints/base.py
apifoncier/endpoints/cartofriches.py
apifoncier/endpoints/dv3f.py
apifoncier/endpoints/dvf_opendata.py
apifoncier/endpoints/ff.py
apifoncier/endpoints/indicateurs.py
apifoncier2-0.1.4.dist-info/licenses/LICENSE
apifoncier2-0.1.4.dist-info/METADATA
apifoncier2-0.1.4.dist-info/WHEEL
apifoncier2-0.1.4.dist-info/top_level.txt
apifoncier2-0.1.4.dist-info/RECORD
