Metadata-Version: 2.4
Name: apifoncier2
Version: 0.1.4
Summary: Utiliser l'API Données foncières du Cerema en python
Author: aherman59
License-Expression: MIT AND (Apache-2.0 OR BSD-2-Clause)
Project-URL: Homepage, https://cerema.github.io/apifoncier/
Keywords: api,datafoncier,foncier
Classifier: Programming Language :: Python
Classifier: Programming Language :: Python :: 3
Requires-Python: >=3.11
License-File: LICENSE
Requires-Dist: geopandas>=1.1.1
Requires-Dist: pandas>=2.3.1
Requires-Dist: requests>=2.32.4
Requires-Dist: tqdm>=4.67.1
Requires-Dist: urllib3>=2.5.0
Dynamic: license-file
